ligo/gracedb/__init__.py
ligo/gracedb/adapter.py
ligo/gracedb/alias.py
ligo/gracedb/cert.py
ligo/gracedb/client.py
ligo/gracedb/exceptions.py
ligo/gracedb/logging.py
ligo/gracedb/rest.py
ligo/gracedb/token.py
ligo/gracedb/utils.py
ligo/gracedb/version.py
ligo/gracedb/cli/__init__.py
ligo/gracedb/cli/client.py
ligo/gracedb/cli/conftest.py
ligo/gracedb/cli/parsers.py
ligo/gracedb/cli/utils.py
ligo/gracedb/cli/commands/__init__.py
ligo/gracedb/cli/commands/add.py
ligo/gracedb/cli/commands/base.py
ligo/gracedb/cli/commands/create.py
ligo/gracedb/cli/commands/delete.py
ligo/gracedb/cli/commands/get.py
ligo/gracedb/cli/commands/list.py
ligo/gracedb/cli/commands/remove.py
ligo/gracedb/cli/commands/search.py
ligo/gracedb/cli/commands/subcommands.py
ligo/gracedb/cli/commands/update.py
ligo/gracedb/cli/commands/tests/__init__.py
ligo/gracedb/cli/commands/tests/test_add.py
ligo/gracedb/cli/commands/tests/test_create.py
ligo/gracedb/cli/commands/tests/test_delete.py
ligo/gracedb/cli/commands/tests/test_get.py
ligo/gracedb/cli/commands/tests/test_level1_commands.py
ligo/gracedb/cli/commands/tests/test_level1_subcommands.py
ligo/gracedb/cli/commands/tests/test_level2_subcommands_help.py
ligo/gracedb/cli/commands/tests/test_list.py
ligo/gracedb/cli/commands/tests/test_remove.py
ligo/gracedb/cli/commands/tests/test_search.py
ligo/gracedb/cli/commands/tests/test_update.py
ligo/gracedb/cli/tests/__init__.py
ligo/gracedb/cli/tests/test_cli.py
ligo/gracedb/cli/tests/test_main.py
ligo/gracedb/test/__init__.py
ligo/gracedb/test/conftest.py
ligo/gracedb/test/test_certificate.py
ligo/gracedb/test/test_client.py
ligo/gracedb/test/test_emobservations.py
ligo/gracedb/test/test_events.py
ligo/gracedb/test/test_files.py
ligo/gracedb/test/test_gwtc.py
ligo/gracedb/test/test_labels.py
ligo/gracedb/test/test_logging.py
ligo/gracedb/test/test_logs.py
ligo/gracedb/test/test_permissions.py
ligo/gracedb/test/test_scitokens.py
ligo/gracedb/test/test_signoffs.py
ligo/gracedb/test/test_superevents.py
ligo_gracedb-2.14.2.dist-info/licenses/LICENSE
ligo_gracedb-2.14.2.dist-info/METADATA
ligo_gracedb-2.14.2.dist-info/WHEEL
ligo_gracedb-2.14.2.dist-info/entry_points.txt
ligo_gracedb-2.14.2.dist-info/top_level.txt
ligo_gracedb-2.14.2.dist-info/RECORD
